{
  "ІІІ етап Всеукраїнського конкурсу-захисту науково-дослідницьких робіт учнів – членів МАН України у 2025 році": {
    "Наукове відділення – економіки": {
      "Міжнародна економіка та аналітика": [
        {
          "№": 1,
          "Прізвище, ім’я, по батькові": "Мокану Валерія Володимирівна",
          "Область": "Дніпропетровська",
          "Клас": 10,
          "Заочне оцінювання": 16.90,
          "Постерний захист": 37.58,
          "Наукова конференція": 28.35,
          "Загальна сума балів": 82.83,
          "Рейтинг": 4,
          "Місце": "ІІІ"
        },
        {
          "№": 2,
          "Прізвище, ім’я, по батькові": "Іванова Євгенія Ігорівна",
          "Область": "Донецька",
          "Клас": 10,
          "Заочне оцінювання": 14.50,
          "Постерний захист": 31.28,
          "Наукова конференція": 23.10,
          "Загальна сума балів": 68.88,
          "Рейтинг": 8
        },
        {
          "№": 3,
          "Прізвище, ім’я, по батькові": "Шовак Євгеній Васильович",
          "Область": "Закарпатська",
          "Клас": 8,
          "Заочне оцінювання": 10.40,
          "Постерний захист": 30.38,
          "Наукова конференція": 29.40,
          "Загальна сума балів": 70.18,
          "Рейтинг": 7
        },
        {
          "№": 4,
          "Прізвище, ім’я, по батькові": "Шутка Марк Володимирович",
          "Область": "Кіровоградська",
          "Клас": 10,
          "Заочне оцінювання": 14.70,
          "Постерний захист": 34.65,
          "Наукова конференція": 25.38,
          "Загальна сума балів": 74.73,
          "Рейтинг": 5
        },
        {
          "№": 5,
          "Прізвище, ім’я, по батькові": "Івасівка Остап Орестович",
          "Область": "Львівська",
          "Клас": 10,
          "Заочне оцінювання": 17.10,
          "Постерний захист": 38.48,
          "Наукова конференція": 31.33,
          "Загальна сума балів": 86.90,
          "Рейтинг": 1,
          "Місце": "І"
        },
        {
          "№": 6,
          "Прізвище, ім’я, по батькові": "Єсін Олександр Олександрович",
          "Область": "Рівненська",
          "Клас": 11,
          "Заочне оцінювання": 15.70,
          "Постерний захист": 33.08,
          "Наукова конференція": 25.55,
          "Загальна сума балів": 74.33,
          "Рейтинг": 6
        },
        {
          "№": 7,
          "Прізвище, ім’я, по батькові": "Пелешок Кирил Вячеславович",
          "Область": "Харківська",
          "Клас": 10,
          "Заочне оцінювання": 15.50,
          "Постерний захист": 37.58,
          "Наукова конференція": 30.10,
          "Загальна сума балів": 83.18,
          "Рейтинг": 3,
          "Місце": "ІІІ"
        },
        {
          "№": 8,
          "Прізвище, ім’я, по батькові": "Євдокименко Ігор Олександрович",
          "Область": "м. Київ",
          "Клас": 11,
          "Заочне оцінювання": 16.30,
          "Постерний захист": 39.38,
          "Наукова конференція": 29.40,
          "Загальна сума балів": 85.08,
          "Рейтинг": 2,
          "Місце": "ІІ"
        }
      ],
      "Прикладна мікроекономіка та підприємництво": [
        {
          "№": 1,
          "Прізвище, ім’я, по батькові": "Мартинюк Михайло Олегович",
          "Область": "Волинська",
          "Клас": 10,
          "Заочне оцінювання": 12.30,
          "Постерний захист": 28.58,
          "Наукова конференція": 26.60,
          "Загальна сума балів": 67.48,
          "Рейтинг": 18
        },
         {
          "№": 2,
          "Прізвище, ім’я, по батькові": "Тернова Евеліна Ігорівна",
          "Область": "Дніпропетровська",
          "Клас": 11,
          "Заочне оцінювання": 12.80,
          "Постерний захист": 29.48,
          "Наукова конференція": 26.25,
          "Загальна сума балів": 68.53,
          "Рейтинг": 17
        },
        {
          "№": 3,
          "Прізвище, ім’я, по батькові": "Деркач Єлизавета Миколаївна",
          "Область": "Житомирська",
          "Клас": 11,
          "Заочне оцінювання": 13.30,
          "Постерний захист": 33.08,
          "Наукова конференція": 30.10,
          "Загальна сума балів": 76.48,
          "Рейтинг": 12
        },
        {
          "№": 4,
          "Прізвище, ім’я, по батькові": "Передерій Артем Олександрович",
          "Область": "Запорізька",
          "Клас": 10,
          "Заочне оцінювання": 12.40,
          "Постерний захист": 33.75,
          "Наукова конференція": 30.63,
          "Загальна сума балів": 76.78,
          "Рейтинг": 10
        },
        {
          "№": 5,
          "Прізвище, ім’я, по батькові": "Метошоп Анастасія Юріївна",
          "Область": "Івано-Франківська",
          "Клас": 10,
          "Заочне оцінювання": 15.10,
          "Постерний захист": 34.20,
          "Наукова конференція": 30.45,
          "Загальна сума балів": 79.75,
          "Рейтинг": 7,
          "Місце": "ІІІ"
        },
        {
          "№": 6,
          "Прізвище, ім’я, по батькові": "Горбач Олександра Олександрівна",
          "Область": "Київська",
          "Клас": "ІІ курс",
          "Заочне оцінювання": 14.00,
          "Постерний захист": 36.90,
          "Наукова конференція": 31.50,
          "Загальна сума балів": 82.40,
          "Рейтинг": 6,
          "Місце": "ІІІ"
        },
        {
          "№": 7,
          "Прізвище, ім’я, по батькові": "Дигдало Ніка Романівна",
          "Область": "Кіровоградська",
          "Клас": 10,
          "Заочне оцінювання": 15.50,
          "Постерний захист": 31.28,
          "Наукова конференція": 27.65,
          "Загальна сума балів": 74.43,
          "Рейтинг": 14
        },
        {
          "№": 8,
          "Прізвище, ім’я, по батькові": "Криса Анастасія Орестівна",
          "Область": "Львівська",
          "Клас": 10,
          "Заочне оцінювання": 17.50,
          "Постерний захист": 42.08,
          "Наукова конференція": 32.03,
          "Загальна сума балів": 91.60,
          "Рейтинг": 3,
          "Місце": "ІІ"
        },
        {
          "№": 9,
          "Прізвище, ім’я, по батькові": "Куліш Валерій Русланович",
          "Область": "Полтавська",
          "Клас": 11,
          "Заочне оцінювання": 14.50,
          "Постерний захист": 37.58,
          "Наукова конференція": 30.63,
          "Загальна сума балів": 82.70,
          "Рейтинг": 5,
          "Місце": "ІІІ"
        },
        {
          "№": 10,
          "Прізвище, ім’я, по батькові": "Мателешко Олеся Олександрівна",
          "Область": "Рівненська",
          "Клас": 11,
          "Заочне оцінювання": 14.90,
          "Постерний захист": 32.18,
          "Наукова конференція": 28.53,
          "Загальна сума балів": 75.60,
          "Рейтинг": 13
        },
        {
          "№": 11,
          "Прізвище, ім’я, по батькові": "Ткачова Марія Сергіївна",
          "Область": "Сумська",
          "Клас": 9,
          "Заочне оцінювання": 17.10,
          "Постерний захист": 38.48,
          "Наукова конференція": 32.90,
          "Загальна сума балів": 88.48,
          "Рейтинг": 4,
          "Місце": "ІІ"
        },
        {
          "№": 12,
          "Прізвище, ім’я, по батькові": "Вірковська Мілана Миколаївна",
          "Область": "Тернопільська",
          "Клас": 9,
          "Заочне оцінювання": 17.50,
          "Постерний захист": 30.60,
          "Наукова конференція": 29.93,
          "Загальна сума балів": 78.03,
          "Рейтинг": 9,
          "Місце": "ІІІ"
        },
        {
          "№": 13,
          "Прізвище, ім’я, по батькові": "Єрьомін Кирило Антонович",
          "Область": "Харківська",
          "Клас": 11,
          "Заочне оцінювання": 16.80,
          "Постерний захист": 43.20,
          "Наукова конференція": 34.13,
          "Загальна сума балів": 94.13,
          "Рейтинг": 1,
          "Місце": "І"
        },
        {
          "№": 14,
          "Прізвище, ім’я, по батькові": "Гридіна Юлія Петрівна",
          "Область": "Херсонська",
          "Клас": 10,
          "Заочне оцінювання": 12.70,
          "Постерний захист": 33.75,
          "Наукова конференція": 30.10,
          "Загальна сума балів": 76.55,
          "Рейтинг": 11
        },
        {
          "№": 15,
          "Прізвище, ім’я, по батькові": "Несторишен Олексій Ігорович",
          "Область": "Хмельницька",
          "Клас": 10,
          "Заочне оцінювання": 13.60,
          "Постерний захист": 35.78,
          "Наукова конференція": 29.40,
          "Загальна сума балів": 78.78,
          "Рейтинг": 8,
          "Місце": "ІІІ"
        },
        {
          "№": 16,
          "Прізвище, ім’я, по батькові": "Лукашенко Назар Романович",
          "Область": "Черкаська",
          "Клас": 11,
          "Заочне оцінювання": 18.00,
          "Постерний захист": 42.53,
          "Наукова конференція": 32.20,
          "Загальна сума балів": 92.73,
          "Рейтинг": 2,
          "Місце": "ІІ"
        },
        {
          "№": 17,
          "Прізвище, ім’я, по батькові": "Шевченко Іван Володимирович",
          "Область": "Чернігівська",
          "Клас": 9,
          "Заочне оцінювання": 13.10,
          "Постерний захист": 30.60,
          "Наукова конференція": 25.90,
          "Загальна сума балів": 69.60,
          "Рейтинг": 16
        },
        {
          "№": 18,
          "Прізвище, ім’я, по батькові": "Бенько Ольга Сергіївна",
          "Область": "м. Київ",
          "Клас": 10,
          "Заочне оцінювання": 13.40,
          "Постерний захист": 31.50,
          "Наукова конференція": 27.13,
          "Загальна сума балів": 72.03,
          "Рейтинг": 15
        }
      ],
      "Фінанси, банківська справа та страхування": [
        {
          "№": 1,
          "Прізвище, ім’я, по батькові": "Савюк Дарія Андріївна",
          "Область": "Волинська",
          "Клас": 9,
          "Заочне оцінювання": 18.30,
          "Постерний захист": 39.60,
          "Наукова конференція": 30.10,
          "Загальна сума балів": 88.00,
          "Рейтинг": 7,
          "Місце": "ІІІ"
        },
        {
          "№": 2,
          "Прізвище, ім’я, по батькові": "Колесник Дмитро Олександрович",
          "Область": "Дніпропетровська",
          "Клас": 10,
          "Заочне оцінювання": 18.80,
          "Постерний захист": 41.40,
          "Наукова конференція": 34.48,
          "Загальна сума балів": 94.68,
          "Рейтинг": 2,
          "Місце": "ІІ"
        },
        {
          "№": 3,
          "Прізвище, ім’я, по батькові": "Мокрецький Андрій Вікторович",
          "Область": "Житомирська",
          "Клас": 11,
          "Заочне оцінювання": 18.80,
          "Постерний захист": 44.33,
          "Наукова конференція": 34.48,
          "Загальна сума балів": 97.60,
          "Рейтинг": 1,
          "Місце": "І"
        },
        {
          "№": 4,
          "Прізвище, ім’я, по батькові": "Кричфалушій Вікторія Іванівна",
          "Область": "Закарпатська",
          "Клас": 11,
          "Заочне оцінювання": 14.90,
          "Постерний захист": 32.18,
          "Наукова конференція": 27.83,
          "Загальна сума балів": 74.90,
          "Рейтинг": 13
        },
        {
          "№": 5,
          "Прізвище, ім’я, по батькові": "Ковальчук Владислав Вадимович",
          "Область": "Київська",
          "Клас": 11,
          "Заочне оцінювання": 17.60,
          "Постерний захист": 35.78,
          "Наукова конференція": 28.70,
          "Загальна сума балів": 82.08,
          "Рейтинг": 11
        },
        {
          "№": 6,
          "Прізвище, ім’я, по батькові": "Смоляник Ангеліна Олегівна",
          "Область": "Кіровоградська",
          "Клас": 11,
          "Заочне оцінювання": 19.60,
          "Постерний захист": 41.18,
          "Наукова конференція": 31.15,
          "Загальна сума балів": 91.93,
          "Рейтинг": 4,
          "Місце": "ІІІ"
        },
        {
          "№": 7,
          "Прізвище, ім’я, по батькові": "Ознамець Ніколь Віталіївна",
          "Область": "Львівська",
          "Клас": 11,
          "Заочне оцінювання": 19.10,
          "Постерний захист": 40.50,
          "Наукова конференція": 32.03,
          "Загальна сума балів": 91.63,
          "Рейтинг": 5,
          "Місце": "ІІІ"
        },
        {
          "№": 8,
          "Прізвище, ім’я, по батькові": "Береза Олександра Костянтинівна",
          "Область": "Полтавська",
          "Клас": 10,
          "Заочне оцінювання": 17.90,
          "Постерний захист": 36.68,
          "Наукова конференція": 31.50,
          "Загальна сума балів": 86.08,
          "Рейтинг": 8
        },
        {
          "№": 9,
          "Прізвище, ім’я, по батькові": "Буднік Софія Олегівна",
          "Область": "Рівненська",
          "Клас": 11,
          "Заочне оцінювання": 16.30,
          "Постерний захист": 41.40,
          "Наукова конференція": 32.03,
          "Загальна сума балів": 89.73,
          "Рейтинг": 6,
          "Місце": "ІІІ"
        },
        {
          "№": 10,
          "Прізвище, ім’я, по батькові": "Гавриленко Родіон Олексійович",
          "Область": "Харківська",
          "Клас": 11,
          "Заочне оцінювання": 19.30,
          "Постерний захист": 42.53,
          "Наукова конференція": 31.50,
          "Загальна сума балів": 93.33,
          "Рейтинг": 3,
          "Місце": "ІІ"
        },
        {
          "№": 11,
          "Прізвище, ім’я, по батькові": "Лопатньов Даніїл Костянтинович",
          "Область": "Херсонська",
          "Клас": 11,
          "Заочне оцінювання": 17.50,
          "Постерний захист": 36.00,
          "Наукова конференція": 28.53,
          "Загальна сума балів": 82.03,
          "Рейтинг": 12
        },
        {
          "№": 12,
          "Прізвище, ім’я, по батькові": "Лапушинська Яна Валеріївна",
          "Область": "Хмельницька",
          "Клас": 10,
          "Заочне оцінювання": 19.60,
          "Постерний захист": 33.08,
          "Наукова конференція": 30.28,
          "Загальна сума балів": 82.95,
          "Рейтинг": 10
        },
        {
          "№": 13,
          "Прізвище, ім’я, по батькові": "Панченко Софія Тарасівна",
          "Область": "м. Київ",
          "Клас": 10,
          "Заочне оцінювання": 18.40,
          "Постерний захист": 36.68,
          "Наукова конференція": 28.70,
          "Загальна сума балів": 83.78,
          "Рейтинг": 9
        }
      ],
      "Макроекономіка та економічна політика": [
        {
          "№": 1,
          "Прізвище, ім’я, по батькові": "Нікітіна Анастасія Андріївна",
          "Область": "Волинська",
          "Клас": 9,
          "Заочне оцінювання": 14.70,
          "Постерний захист": 37.58,
          "Наукова конференція": 28.70,
          "Загальна сума балів": 80.98,
          "Рейтинг": 14
        },
        {
          "№": 2,
          "Прізвище, ім’я, по батькові": "Абраменкова Анна Костянтинівна",
          "Область": "Дніпропетровська",
          "Клас": 10,
          "Заочне оцінювання": 14.80,
          "Постерний захист": 39.60,
          "Наукова конференція": 32.03,
          "Загальна сума балів": 86.43,
          "Рейтинг": 5,
          "Місце": "ІІІ"
        },
        {
          "№": 3,
          "Прізвище, ім’я, по батькові": "Кравчук Олександра Юріївна",
          "Область": "Житомирська",
          "Клас": 10,
          "Заочне оцінювання": 19.20,
          "Постерний захист": 34.65,
          "Наукова конференція": 25.73,
          "Загальна сума балів": 79.58,
          "Рейтинг": 15
        },
        {
          "№": 4,
          "Прізвище, ім’я, по батькові": "Шарга Ярослав Євгенович",
          "Область": "Закарпатська",
          "Клас": 11,
          "Заочне оцінювання": 16.10,
          "Постерний захист": 38.48,
          "Наукова конференція": 30.28,
          "Загальна сума балів": 84.85,
          "Рейтинг": 8,
          "Місце": "ІІІ"
        },
        {
          "№": 5,
          "Прізвище, ім’я, по батькові": "Борсук Богдана Миколаївна",
          "Область": "Запорізька",
          "Клас": 11,
          "Заочне оцінювання": 16.80,
          "Постерний захист": 42.08,
          "Наукова конференція": 29.93,
          "Загальна сума балів": 88.80,
          "Рейтинг": 3,
          "Місце": "ІІ"
        },
        {
          "№": 6,
          "Прізвище, ім’я, по батькові": "Гандера Богдана Василівна",
          "Область": "Івано-Франківська",
          "Клас": 9,
          "Заочне оцінювання": 17.40,
          "Постерний захист": 38.48,
          "Наукова конференція": 32.03,
          "Загальна сума балів": 87.90,
          "Рейтинг": 4,
          "Місце": "ІІ"
        },
        {
          "№": 7,
          "Прізвище, ім’я, по батькові": "Сторожук Іванна Олександрівна",
          "Область": "Кіровоградська",
          "Клас": 11,
          "Заочне оцінювання": 18.00,
          "Постерний захист": 36.90,
          "Наукова конференція": 30.80,
          "Загальна сума балів": 85.70,
          "Рейтинг": 7,
          "Місце": "ІІІ"
        },
        {
          "№": 8,
          "Прізвище, ім’я, по батькові": "Томашевська Інна Ростиславівна",
          "Область": "Львівська",
          "Клас": 11,
          "Заочне оцінювання": 18.30,
          "Постерний захист": 42.98,
          "Наукова конференція": 35.00,
          "Загальна сума балів": 96.28,
          "Рейтинг": 1,
          "Місце": "І"
        },
        {
          "№": 9,
          "Прізвище, ім’я, по батькові": "Удовіченко Тетяна Сергіївна",
          "Область": "Полтавська",
          "Клас": 9,
          "Заочне оцінювання": 17.60,
          "Постерний захист": 37.58,
          "Наукова конференція": 28.53,
          "Загальна сума балів": 83.70,
          "Рейтинг": 9
        },
        {
          "№": 10,
          "Прізвище, ім’я, по батькові": "Олійник Андрій Володимирович",
          "Область": "Рівненська",
          "Клас": 10,
          "Заочне оцінювання": 17.10,
          "Постерний захист": 35.10,
          "Наукова конференція": 30.10,
          "Загальна сума балів": 82.30,
          "Рейтинг": 11
        },
        {
          "№": 11,
          "Прізвище, ім’я, по батькові": "Салогуб Марія Олександрівна",
          "Область": "Сумська",
          "Клас": 11,
          "Заочне оцінювання": 17.20,
          "Постерний захист": 35.78,
          "Наукова конференція": 28.53,
          "Загальна сума балів": 81.50,
          "Рейтинг": 12
        },
        {
          "№": 12,
          "Прізвище, ім’я, по батькові": "Погорєлова Єлизавета Станіславівна",
          "Область": "Харківська",
          "Клас": 11,
          "Заочне оцінювання": 16.30,
          "Постерний захист": 36.68,
          "Наукова конференція": 28.35,
          "Загальна сума балів": 81.33,
          "Рейтинг": 13
        },
        {
          "№": 13,
          "Прізвище, ім’я, по батькові": "Дудченко Назар Анатолійович",
          "Область": "Хмельницька",
          "Клас": 10,
          "Заочне оцінювання": 19.20,
          "Постерний захист": 37.58,
          "Наукова конференція": 29.40,
          "Загальна сума балів": 86.18,
          "Рейтинг": 6,
          "Місце": "ІІІ"
        },
        {
          "№": 14,
          "Прізвище, ім’я, по батькові": "Бабченко Марія Тарасівна",
          "Область": "Черкаська",
          "Клас": 10,
          "Заочне оцінювання": 16.30,
          "Постерний захист": 37.58,
          "Наукова конференція": 29.40,
          "Загальна сума балів": 83.28,
          "Рейтинг": 10
        },
        {
          "№": 15,
          "Прізвище, ім’я, по батькові": "Бодня Данило Юрійович",
          "Область": "м. Київ",
          "Клас": 10,
          "Заочне оцінювання": 18.80,
          "Постерний захист": 42.08,
          "Наукова конференція": 34.13,
          "Загальна сума балів": 95.00,
          "Рейтинг": 2,
          "Місце": "ІІ"
        }
      ],
      "Менеджмент та маркетинг": [
        {
          "№": 1,
          "Прізвище, ім’я, по батькові": "Середа Віктор Олександрович",
          "Область": "Вінницька",
          "Клас": 11,
          "Заочне оцінювання": 15.40,
          "Постерний захист": 38.93,
          "Наукова конференція": 32.55,
          "Загальна сума балів": 86.88,
          "Рейтинг": 9,
          "Місце": "ІІІ"
        },
        {
          "№": 2,
          "Прізвище, ім’я, по батькові": "Лорві Давид Олександрович",
          "Область": "Волинська",
          "Клас": 9,
          "Заочне оцінювання": 15.50,
          "Постерний захист": 36.00,
          "Наукова конференція": 28.00,
          "Загальна сума балів": 79.50,
          "Рейтинг": 14
        },
        {
          "№": 3,
          "Прізвище, ім’я, по батькові": "Бурлаченко Олександр Сергійович",
          "Область": "Дніпропетровська",
          "Клас": 11,
          "Заочне оцінювання": 13.50,
          "Постерний захист": 36.00,
          "Наукова конференція": 26.60,
          "Загальна сума балів": 76.10,
          "Рейтинг": 16
        },
        {
          "№": 4,
          "Прізвище, ім’я, по батькові": "Поспєлова Альона Анатоліївна",
          "Область": "Донецька",
          "Клас": 11,
          "Заочне оцінювання": 18.40,
          "Постерний захист": 42.98,
          "Наукова конференція": 33.60,
          "Загальна сума балів": 94.98,
          "Рейтинг": 3,
          "Місце": "ІІ"
        },
        {
          "№": 5,
          "Прізвище, ім’я, по батькові": "Романюк Євген Олегович",
          "Область": "Житомирська",
          "Клас": 11,
          "Заочне оцінювання": 16.80,
          "Постерний захист": 44.10,
          "Наукова конференція": 33.60,
          "Загальна сума балів": 94.50,
          "Рейтинг": 4,
          "Місце": "ІІ"
        },
        {
          "№": 6,
          "Прізвище, ім’я, по батькові": "Горват Олександра Юріївна",
          "Область": "Закарпатська",
          "Клас": 8,
          "Заочне оцінювання": 16.20,
          "Постерний захист": 36.00,
          "Наукова конференція": 28.18,
          "Загальна сума балів": 80.38,
          "Рейтинг": 12
        },
        {
          "№": 7,
          "Прізвище, ім’я, по батькові": "Чурякова Катерина Віталіївна",
          "Область": "Запорізька",
          "Клас": 11,
          "Заочне оцінювання": 14.60,
          "Постерний захист": 40.50,
          "Наукова конференція": 32.73,
          "Загальна сума балів": 87.83,
          "Рейтинг": 7,
          "Місце": "ІІІ"
        },
        {
          "№": 8,
          "Прізвище, ім’я, по батькові": "Микусевич Дар’я Іванівна",
          "Область": "Київська",
          "Клас": 10,
          "Заочне оцінювання": 18.40,
          "Постерний захист": 38.03,
          "Наукова конференція": 25.73,
          "Загальна сума балів": 82.15,
          "Рейтинг": 10
        },
        {
          "№": 9,
          "Прізвище, ім’я, по батькові": "Морозов Ярослав Віталійович",
          "Область": "Кіровоградська",
          "Клас": 10,
          "Заочне оцінювання": 17.10,
          "Постерний захист": 34.43,
          "Наукова конференція": 23.98,
          "Загальна сума балів": 75.50,
          "Рейтинг": 17
        },
        {
          "№": 10,
          "Прізвище, ім’я, по батькові": "Павлик Софія Василівна",
          "Область": "Львівська",
          "Клас": 10,
          "Заочне оцінювання": 19.60,
          "Постерний захист": 45.00,
          "Наукова конференція": 35.00,
          "Загальна сума балів": 99.60,
          "Рейтинг": 1,
          "Місце": "І"
        },
        {
          "№": 11,
          "Прізвище, ім’я, по батькові": "Костянецька Катерина Антонівна",
          "Область": "Полтавська",
          "Клас": 11,
          "Заочне оцінювання": 18.70,
          "Постерний захист": 41.40,
          "Наукова конференція": 32.38,
          "Загальна сума балів": 92.48,
          "Рейтинг": 5,
          "Місце": "ІІІ"
        },
        {
          "№": 12,
          "Прізвище, ім’я, по батькові": "Кравчук Богдан Тарасович",
          "Область": "Рівненська",
          "Клас": 11,
          "Заочне оцінювання": 16.90,
          "Постерний захист": 37.13,
          "Наукова конференція": 28.00,
          "Загальна сума балів": 82.03,
          "Рейтинг": 11
        },
        {
          "№": 13,
          "Прізвище, ім’я, по батькові": "Сідерко Олександра Сергіївна",
          "Область": "Сумська",
          "Клас": 10,
          "Заочне оцінювання": 14.50,
          "Постерний захист": 36.00,
          "Наукова конференція": 29.75,
          "Загальна сума балів": 80.25,
          "Рейтинг": 13
        },
        {
          "№": 14,
          "Прізвище, ім’я, по батькові": "Кінас Микола Олександрович",
          "Область": "Харківська",
          "Клас": 10,
          "Заочне оцінювання": 9.90,
          "Постерний захист": 42.08,
          "Наукова конференція": 26.78,
          "Загальна сума балів": 78.75,
          "Рейтинг": 15
        },
        {
          "№": 15,
          "Прізвище, ім’я, по батькові": "Пунда Маргаріта Олександрівна",
          "Область": "Хмельницька",
          "Клас": 9,
          "Заочне оцінювання": 19.60,
          "Постерний захист": 36.00,
          "Наукова конференція": 31.50,
          "Загальна сума балів": 87.10,
          "Рейтинг": 8,
          "Місце": "ІІІ"
        },
        {
          "№": 16,
          "Прізвище, ім’я, по батькові": "Москаленко Дар’я Анатоліївна",
          "Область": "Чернігівська",
          "Клас": 10,
          "Заочне оцінювання": 19.60,
          "Постерний захист": 45.00,
          "Наукова конференція": 33.60,
          "Загальна сума балів": 98.20,
          "Рейтинг": 2,
          "Місце": "ІІ"
        },
        {
          "№": 17,
          "Прізвище, ім’я, по батькові": "Слабко Милослава Іванівна",
          "Область": "м. Київ",
          "Клас": 11,
          "Заочне оцінювання": 17.90,
          "Постерний захист": 39.60,
          "Наукова конференція": 31.50,
          "Загальна сума балів": 89.00,
          "Рейтинг": 6,
          "Місце": "ІІІ"
        }
      ]
    }
  }
}
